<annotation>
	<folder>train</folder>
	<filename>180.jpg</filename>
	<path>C:\tfsample\train\180.jpg</path>
	<source>
		<database>Unknown</database>
	</source>
	<size>
		<width>1861</width>
		<height>879</height>
		<depth>3</depth>
	</size>
	<segmented>0</segmented>
	<object>
		<name>v_s</name>
		<pose>Unspecified</pose>
		<truncated>0</truncated>
		<difficult>0</difficult>
		<bndbox>
			<xmin>881</xmin>
			<ymin>308</ymin>
			<xmax>1014</xmax>
			<ymax>535</ymax>
		</bndbox>
	</object>
	<object>
		<name>v_s</name>
		<pose>Unspecified</pose>
		<truncated>0</truncated>
		<difficult>0</difficult>
		<bndbox>
			<xmin>1196</xmin>
			<ymin>43</ymin>
			<xmax>1444</xmax>
			<ymax>211</ymax>
		</bndbox>
	</object>
	<object>
		<name>v_s</name>
		<pose>Unspecified</pose>
		<truncated>0</truncated>
		<difficult>0</difficult>
		<bndbox>
			<xmin>230</xmin>
			<ymin>347</ymin>
			<xmax>383</xmax>
			<ymax>643</ymax>
		</bndbox>
	</object>
</annotation>
